[{"title":"Blog Title NNujuSlg8k","description":"Description for UvEd4AS0QZyaPyOu02WO blog post.","author":"kDO5l@example.com","id":"1733241242717461"},{"title":"Blog Title cWCSSE53mq","description":"Description for X01mM2aUQaAbv04MoadG blog post.","author":"lwimD@example.com","id":"1733241284668138"},{"title":"Blog Title NH2tSlFa4g","description":"Description for DZog13BR56pV2VMPxaB2 blog post.","author":"kYZKT@example.com","id":"1733241331185349"},{"title":"Blog Title taJP6NzMYk","description":"Description for nH2qeA5hb1BtYj7Y6gIm blog post.","author":"kmyQQ@example.com","id":"1733241441233733"},{"title":"Blog Title HEguopeQG6","description":"Description for eMNexENlcn7kl6agGas4 blog post.","author":"D9VKG@example.com","id":"1733241457068756"},{"title":"Blog Title 5ADx8Ksnlx","description":"Description for I7v4fqiu5maTrX4EaIhg blog post.","author":"RagGK@example.com","id":"1733241482553699"}]